SupplyNetPy/__init__.py
SupplyNetPy/Components/__init__.py
SupplyNetPy/Components/core.py
SupplyNetPy/Components/logger.py
SupplyNetPy/Components/utilities.py
supplynetpy-0.1.6.dist-info/METADATA
supplynetpy-0.1.6.dist-info/WHEEL
supplynetpy-0.1.6.dist-info/licenses/LICENSE
supplynetpy-0.1.6.dist-info/RECORD
