Metadata-Version: 2.4
Name: supplynetpy
Version: 0.1.6
Summary: Python Library for Modeling and Discrete Event Simulation of Supply Chains
Project-URL: Homepage, https://supplychainsimulation.github.io/SupplyNetPy/
Author-email: Tushar Lone <tusharlone28@gmail.com>, Neha Karanjkar <nehak@iitgoa.ac.in>, Lekshmi P <Lekshmi20231101@iitgoa.ac.in>
Maintainer-email: Tushar Lone <tusharlone28@gmail.com>
License: MIT License
License-File: LICENSE
Keywords: discrete event simulation,inventory,modeling,simulation,supply chain
Classifier: Development Status :: 2 - Pre-Alpha
Classifier: Intended Audience :: Science/Research
Classifier: License :: OSI Approved :: MIT License
Classifier: Programming Language :: Python :: 3
Classifier: Programming Language :: Python :: 3.8
Classifier: Programming Language :: Python :: 3.9
Classifier: Programming Language :: Python :: 3.10
Classifier: Programming Language :: Python :: 3.11
Classifier: Topic :: Scientific/Engineering
Requires-Python: >=3.6
Requires-Dist: simpy
